{
  "ids": {
    "site_id": "brewtonplumbingservicellc",
    "place_id": "ChIJiZTNf8yuIgwRvMjsM42TByQ",
    "google_id": "0xc22aecc7fcd9489:0x2407938d33ecc8bc",
    "owner_id": 116087792742898528382
  },
  "basic_info": {
    "name": "Brewton Plumbing Service LLC",
    "reviews_link": "https://search.google.com/local/reviews?placeid=ChIJiZTNf8yuIgwRvMjsM42TByQ&q=plumber,+72952,+Rudy,+AR,+US&authuser=0&hl=en&gl=US",
    "phone": "+1 479-459-4283",
    "query": "plumber, 72952, Rudy, AR, US",
    "name_for_emails": "Brewton Plumbing Service",
    "site": "",
    "subtypes": "Plumber, Service establishment",
    "category": "Plumber",
    "type": "Plumber",
    "phone.phones_enricher.carrier_type": "mobile",
    "phone.phones_enricher.carrier_name": "NEW CINGULAR WIRELESS PCS, LLC - IL",
    "full_address": "",
    "borough": "",
    "street": "",
    "city": "",
    "postal_code": "",
    "state": "",
    "us_state": "",
    "country": "",
    "country_code": "",
    "latitude": 35.3477315,
    "longitude": -94.1926943,
    "h3": "8926e91844bffff",
    "time_zone": "America/Chicago",
    "plus_code": "",
    "area_service": "TRUE",
    "rating": 5,
    "reviews": 65,
    "reviews_tags": "",
    "reviews_per_score": "",
    "photos_count": 192,
    "photo": "https://lh5.googleusercontent.com/p/AF1QipOAxn16ubH3Mq8aH6tMwzmWBUfmuH0-vg4z-_UP=w800-h500-k-no",
    "street_view": "https://lh5.googleusercontent.com/p/AF1QipOAxn16ubH3Mq8aH6tMwzmWBUfmuH0-vg4z-_UP=w1600-h1000-k-no",
    "located_in": "",
    "working_hours": "{\"Monday\": \"Open 24 hours\", \"Tuesday\": \"Open 24 hours\", \"Wednesday\": \"Open 24 hours\", \"Thursday\": \"Open 24 hours\", \"Friday\": \"Open 24 hours\", \"Saturday\": \"Open 24 hours\", \"Sunday\": \"Open 24 hours\"}",
    "working_hours_old_format": "Monday:Open 24 hours|Tuesday:Open 24 hours|Wednesday:Open 24 hours|Thursday:Open 24 hours|Friday:Open 24 hours|Saturday:Open 24 hours|Sunday:Open 24 hours",
    "other_hours": "",
    "popular_times": "",
    "business_status": "OPERATIONAL",
    "about": "{\"Service options\": {\"Language assistance\": \"English\"}, \"Payments\": {\"Credit cards\": true}}",
    "range": "",
    "posts": "",
    "logo": "https://lh5.googleusercontent.com/-waDHpZT7ivE/AAAAAAAAAAI/AAAAAAAAAAA/YQ_l83TXDYk/s44-p-k-no-ns-nd/photo.jpg",
    "description": "",
    "typical_time_spent": "",
    "verified": "TRUE",
    "owner_id": 116087792742898528382,
    "owner_title": "Brewton Plumbing Service LLC",
    "owner_link": "https://www.google.com/maps/contrib/116087792742898528382",
    "reservation_links": "",
    "booking_appointment_link": "",
    "menu_link": "",
    "order_links": "",
    "location_link": "https://www.google.com/maps/place/Brewton+Plumbing+Service+LLC/@35.3477315,-94.1926943,14z/data=!4m8!1m2!2m1!1sBrewton+Plumbing+Service+LLC!3m4!1s0xc22aecc7fcd9489:0x2407938d33ecc8bc!8m2!3d35.3477315!4d-94.1926943",
    "location_reviews_link": "https://www.google.com/maps/place/Brewton+Plumbing+Service+LLC/@35.3477315,-94.1926943,13.99z/data=!4m16!1m7!3m6!1s0xc22aecc7fcd9489:0x2407938d33ecc8bc!2sBrewton+Plumbing+Service+LLC!8m2!3d35.3477315!4d-94.1926943!16s%2Fg%2F11ckvg1dmb!3m7!1s0xc22aecc7fcd9489:0x2407938d33ecc8bc!8m2!3d35.3477315!4d-94.1926943!9m1!1b1!16s%2Fg%2F11ckvg1dmb?entry=ttu",
    "place_id": "ChIJiZTNf8yuIgwRvMjsM42TByQ",
    "google_id": "0xc22aecc7fcd9489:0x2407938d33ecc8bc",
    "cid": 2596205944873207996,
    "reviews_id": 2596205944873207996,
    "located_google_id": "",
    "email_1": "brewtonplumbing@gmail.com",
    "email_1.emails_validator.status": "RECEIVING",
    "email_1.emails_validator.status_details": "SMTP validated",
    "email_1_full_name": "",
    "email_1_first_name": "",
    "email_1_last_name": "",
    "email_1_title": "",
    "email_1_phone": "",
    "email_2": "",
    "email_2.emails_validator.status": "",
    "email_2.emails_validator.status_details": "",
    "email_2_full_name": "",
    "email_2_first_name": "",
    "email_2_last_name": "",
    "email_2_title": "",
    "email_2_phone": "",
    "email_3": "",
    "email_3.emails_validator.status": "",
    "email_3.emails_validator.status_details": "",
    "email_3_full_name": "",
    "email_3_first_name": "",
    "email_3_last_name": "",
    "email_3_title": "",
    "email_3_phone": "",
    "phone_1": 14794594283,
    "phone_1.phones_enricher.carrier_type": "mobile",
    "phone_1.phones_enricher.carrier_name": "NEW CINGULAR WIRELESS PCS, LLC - IL",
    "phone_2": "",
    "phone_3": "",
    "facebook": "https://www.facebook.com/people/Brewton-Plumbing-Service-LLC/100078886325905/",
    "instagram": "",
    "linkedin": "",
    "tiktok": "",
    "medium": "",
    "reddit": "",
    "skype": "",
    "snapchat": "",
    "telegram": "",
    "whatsapp": "",
    "twitter": "",
    "vimeo": "",
    "youtube": "",
    "github": "",
    "crunchbase": "",
    "website_title": "",
    "website_generator": "",
    "website_description": "",
    "website_keywords": "",
    "website_has_fb_pixel": "",
    "website_has_google_tag": ""
  },
  "review_trends": {
    "monthly_reviews": {
      "2024-05": 6.0,
      "2024-06": 2.0,
      "2024-07": 1.0,
      "2024-10": 5.0,
      "2024-11": 4.0,
      "2024-12": 1.0,
      "2025-01": 4.0,
      "2025-02": 2.0,
      "2023-09": 1.0,
      "2023-11": 3.0,
      "2024-01": 4.0,
      "2024-08": 4.0,
      "2023-12": 1.0,
      "2024-09": 1.0,
      "2023-06": 4.0,
      "2024-02": 7.0,
      "2024-03": 7.0,
      "2024-04": 14.0
    },
    "yearly_totals": {},
    "total_reviews": 65,
    "owner_responses": 0
  },
  "scores": {
    "photo_score": 0,
    "facebook_score": 0
  }
}