{
  "ids": {
    "site_id": "johnnythomasplumbing",
    "place_id": "ChIJJUc7qlIm1IcRx-cCCiI_yP0",
    "google_id": "0x87d42652aa3b4725:0xfdc83f220a02e7c7",
    "owner_id": 110174052809371399937
  },
  "basic_info": {
    "name": "Johnny Thomas Plumbing",
    "reviews_link": "https://search.google.com/local/reviews?placeid=ChIJJUc7qlIm1IcRx-cCCiI_yP0&q=plumber,+72412,+Beech+Grove,+AR,+US&authuser=0&hl=en&gl=US",
    "phone": "+1 501-276-4225",
    "query": "plumber, 72412, Beech Grove, AR, US",
    "name_for_emails": "Johnny Thomas Plumbing",
    "site": "",
    "subtypes": "Plumber, Service establishment",
    "category": "Plumber",
    "type": "Plumber",
    "phone.phones_enricher.carrier_type": "mobile",
    "phone.phones_enricher.carrier_name": "NEW CINGULAR WIRELESS PCS, LLC - IL",
    "full_address": "",
    "borough": "",
    "street": "",
    "city": "",
    "postal_code": "",
    "state": "",
    "us_state": "",
    "country": "",
    "country_code": "",
    "latitude": 36.1056242,
    "longitude": -90.7795708,
    "h3": "89265d4c493ffff",
    "time_zone": "America/Chicago",
    "plus_code": "",
    "area_service": "TRUE",
    "rating": 3.8,
    "reviews": 23,
    "reviews_tags": "",
    "reviews_per_score": "",
    "photos_count": 4,
    "photo": "https://lh5.googleusercontent.com/p/AF1QipNnKmCTbVOgtAcxY9Pfq3ETcbxHGDiDZEQiQA6e=w800-h500-k-no",
    "street_view": "https://lh5.googleusercontent.com/p/AF1QipNnKmCTbVOgtAcxY9Pfq3ETcbxHGDiDZEQiQA6e=w1600-h1000-k-no",
    "located_in": "",
    "working_hours": "{\"Monday\": \"7AM-3:30PM\", \"Tuesday\": \"7AM-3:30PM\", \"Wednesday\": \"7AM-3:30PM\", \"Thursday\": \"7AM-3:30PM\", \"Friday\": \"7AM-3:30PM\", \"Saturday\": \"Closed\", \"Sunday\": \"Closed\"}",
    "working_hours_old_format": "Monday:7AM-3:30PM|Tuesday:7AM-3:30PM|Wednesday:7AM-3:30PM|Thursday:7AM-3:30PM|Friday:7AM-3:30PM|Saturday:Closed|Sunday:Closed",
    "other_hours": "",
    "popular_times": "",
    "business_status": "OPERATIONAL",
    "about": "{}",
    "range": "",
    "posts": "",
    "logo": "https://lh4.googleusercontent.com/-cIWX5YLliuA/AAAAAAAAAAI/AAAAAAAAAAA/L88jCJxfnSA/s44-p-k-no-ns-nd/photo.jpg",
    "description": "",
    "typical_time_spent": "",
    "verified": "TRUE",
    "owner_id": 110174052809371399937,
    "owner_title": "Johnny Thomas Plumbing",
    "owner_link": "https://www.google.com/maps/contrib/110174052809371399937",
    "reservation_links": "",
    "booking_appointment_link": "",
    "menu_link": "",
    "order_links": "",
    "location_link": "https://www.google.com/maps/place/Johnny+Thomas+Plumbing/@36.1056242,-90.7795708,14z/data=!4m8!1m2!2m1!1sJohnny+Thomas+Plumbing!3m4!1s0x87d42652aa3b4725:0xfdc83f220a02e7c7!8m2!3d36.1056242!4d-90.7795708",
    "location_reviews_link": "https://www.google.com/maps/place/Johnny+Thomas+Plumbing/@36.1056242,-90.7795708,13.99z/data=!4m16!1m7!3m6!1s0x87d42652aa3b4725:0xfdc83f220a02e7c7!2sJohnny+Thomas+Plumbing!8m2!3d36.1056242!4d-90.7795708!16s%2Fg%2F11ckvg1dmb!3m7!1s0x87d42652aa3b4725:0xfdc83f220a02e7c7!8m2!3d36.1056242!4d-90.7795708!9m1!1b1!16s%2Fg%2F11ckvg1dmb?entry=ttu",
    "place_id": "ChIJJUc7qlIm1IcRx-cCCiI_yP0",
    "google_id": "0x87d42652aa3b4725:0xfdc83f220a02e7c7",
    "cid": 18286935702367299527,
    "reviews_id": -159808371342252089,
    "located_google_id": "",
    "email_1": "thomas@thomasplumbingnc.com",
    "email_1.emails_validator.status": "RECEIVING",
    "email_1.emails_validator.status_details": "SMTP validated",
    "email_1_full_name": "",
    "email_1_first_name": "",
    "email_1_last_name": "",
    "email_1_title": "",
    "email_1_phone": "",
    "email_2": "",
    "email_2.emails_validator.status": "",
    "email_2.emails_validator.status_details": "",
    "email_2_full_name": "",
    "email_2_first_name": "",
    "email_2_last_name": "",
    "email_2_title": "",
    "email_2_phone": "",
    "email_3": "",
    "email_3.emails_validator.status": "",
    "email_3.emails_validator.status_details": "",
    "email_3_full_name": "",
    "email_3_first_name": "",
    "email_3_last_name": "",
    "email_3_title": "",
    "email_3_phone": "",
    "phone_1": 19109043104,
    "phone_1.phones_enricher.carrier_type": "",
    "phone_1.phones_enricher.carrier_name": "",
    "phone_2": "",
    "phone_3": "",
    "facebook": "https://www.facebook.com/thomasplumbingnc/photos/a.452405398162473/4308116962591278/?type=3",
    "instagram": "",
    "linkedin": "",
    "tiktok": "",
    "medium": "",
    "reddit": "",
    "skype": "",
    "snapchat": "",
    "telegram": "",
    "whatsapp": "",
    "twitter": "",
    "vimeo": "",
    "youtube": "",
    "github": "",
    "crunchbase": "",
    "website_title": "",
    "website_generator": "",
    "website_description": "",
    "website_keywords": "",
    "website_has_fb_pixel": "",
    "website_has_google_tag": ""
  },
  "review_trends": {
    "monthly_reviews": {
      "2024-10": 1.0,
      "2020-02": 1.0,
      "2020-03": 5.0,
      "2020-04": 1.0,
      "2020-06": 1.0,
      "2020-12": 1.0,
      "2021-06": 1.0,
      "2021-11": 1.0,
      "2022-05": 1.0,
      "2022-06": 1.0,
      "2022-08": 1.0,
      "2022-09": 1.0,
      "2023-03": 2.0,
      "2023-09": 2.0,
      "2023-10": 1.0,
      "2023-11": 1.0,
      "2024-01": 1.0
    },
    "yearly_totals": {},
    "total_reviews": 23,
    "owner_responses": 0
  },
  "scores": {
    "photo_score": 0,
    "facebook_score": 0
  }
}